odoo/addons/odoo_project_changelog/README.rst
odoo/addons/odoo_project_changelog/__init__.py
odoo/addons/odoo_project_changelog/__manifest__.py
odoo/addons/odoo_project_changelog/data/queue_job.xml
odoo/addons/odoo_project_changelog/models/__init__.py
odoo/addons/odoo_project_changelog/models/odoo_project.py
odoo/addons/odoo_project_changelog/models/odoo_project_repository.py
odoo/addons/odoo_project_changelog/readme/CONTRIBUTORS.md
odoo/addons/odoo_project_changelog/readme/DESCRIPTION.md
odoo/addons/odoo_project_changelog/report/ir_actions_report.xml
odoo/addons/odoo_project_changelog/report/odoo_project_changelog.xml
odoo/addons/odoo_project_changelog/security/ir.model.access.csv
odoo/addons/odoo_project_changelog/static/description/icon.png
odoo/addons/odoo_project_changelog/static/description/index.html
odoo/addons/odoo_project_changelog/static/img/changelog.png
odoo/addons/odoo_project_changelog/utils/__init__.py
odoo/addons/odoo_project_changelog/utils/scanner.py
odoo/addons/odoo_project_changelog/views/odoo_project.xml
odoo_addon_odoo_project_changelog-16.0.1.0.1.dist-info/METADATA
odoo_addon_odoo_project_changelog-16.0.1.0.1.dist-info/WHEEL
odoo_addon_odoo_project_changelog-16.0.1.0.1.dist-info/top_level.txt
odoo_addon_odoo_project_changelog-16.0.1.0.1.dist-info/RECORD
